jnt_django_graphene_toolbox/__init__.py
jnt_django_graphene_toolbox/apps.py
jnt_django_graphene_toolbox/connections/__init__.py
jnt_django_graphene_toolbox/connections/model.py
jnt_django_graphene_toolbox/errors/__init__.py
jnt_django_graphene_toolbox/errors/authentication_failed.py
jnt_django_graphene_toolbox/errors/base.py
jnt_django_graphene_toolbox/errors/input.py
jnt_django_graphene_toolbox/errors/not_found.py
jnt_django_graphene_toolbox/errors/permission_denied.py
jnt_django_graphene_toolbox/fields/__init__.py
jnt_django_graphene_toolbox/fields/image.py
jnt_django_graphene_toolbox/fields/model_connection.py
jnt_django_graphene_toolbox/filters/__init__.py
jnt_django_graphene_toolbox/filters/enum_multiple.py
jnt_django_graphene_toolbox/filters/integer.py
jnt_django_graphene_toolbox/filters/integers_array.py
jnt_django_graphene_toolbox/filters/mixins/__init__.py
jnt_django_graphene_toolbox/filters/mixins/camel_cased_ordering.py
jnt_django_graphene_toolbox/filters/mixins/nulls_always_last_ordering.py
jnt_django_graphene_toolbox/filters/ordering.py
jnt_django_graphene_toolbox/filters/search.py
jnt_django_graphene_toolbox/filters/sort.py
jnt_django_graphene_toolbox/filters/strings_array.py
jnt_django_graphene_toolbox/helpers/__init__.py
jnt_django_graphene_toolbox/helpers/generics.py
jnt_django_graphene_toolbox/helpers/selected_fields.py
jnt_django_graphene_toolbox/mutations/__init__.py
jnt_django_graphene_toolbox/mutations/base.py
jnt_django_graphene_toolbox/mutations/serializer.py
jnt_django_graphene_toolbox/nodes/__init__.py
jnt_django_graphene_toolbox/nodes/model.py
jnt_django_graphene_toolbox/types/__init__.py
jnt_django_graphene_toolbox/types/model.py
jnt_django_graphene_toolbox/views/__init__.py
jnt_django_graphene_toolbox/views/api.py
jnt_django_graphene_toolbox/views/playground.py
jnt_django_graphene_toolbox-0.5.1.dist-info/WHEEL
jnt_django_graphene_toolbox-0.5.1.dist-info/METADATA
jnt_django_graphene_toolbox-0.5.1.dist-info/RECORD
