Metadata-Version: 2.1
Name: jnt-django-graphene-toolbox
Version: 0.5.1
Summary: 
Author: junte
Author-email: tech@junte.ru
Requires-Python: >=3.10,<4.0
Classifier: Environment :: Web Environment
Classifier: Intended Audience :: Developers
Classifier: License :: OSI Approved :: MIT License
Classifier: Operating System :: OS Independent
Classifier: Programming Language :: Python :: 3
Classifier: Programming Language :: Python :: 3.10
Classifier: Programming Language :: Python :: 3.11
Classifier: Topic :: Software Development :: Libraries :: Python Modules
Requires-Dist: django (>=4.1)
Requires-Dist: django-filter
Requires-Dist: djangorestframework
Requires-Dist: graphene-file-upload
Requires-Dist: graphene_django
Requires-Dist: jnt_django_toolbox
